<?xml version="1.0" encoding="utf-8"?>
<odoo>
    <data>

        <record id="view_base_language_install" model="ir.ui.view">
            <field name="name">Load a Translation</field>
            <field name="model">base.language.install</field>
            <field name="arch" type="xml">
                <form string="Load a Translation">
                    <group>
                        <field name="lang_ids" widget="many2many_tags" context="{'active_test': False}"/>
                        <field name="overwrite" groups="base.group_no_one"/>
                    </group>
                    <footer>
                        <button name="lang_install" string="Add" type="object" class="btn-primary"/>
                        <button special="cancel" data-hotkey="z" string="Cancel" class="btn-secondary"/>
                    </footer>
                </form>
           </field>
        </record>

        <record id="action_view_base_language_install" model="ir.actions.act_window">
            <field name="name">Add Languages</field>
            <field name="type">ir.actions.act_window</field>
            <field name="res_model">base.language.install</field>
            <field name="view_mode">form</field>
            <field name="target">new</field>
        </record>
    </data>
</odoo>
